pydea_labjc/__init__.py
pydea_labjc/normalization.py
pydea_labjc/pdd.py
pydea_labjc/prework.py
pydea_labjc/stats.py
pydea_labjc/utils.py
pydea_labjc-0.1.0.dist-info/LICENSE
pydea_labjc-0.1.0.dist-info/METADATA
pydea_labjc-0.1.0.dist-info/WHEEL
pydea_labjc-0.1.0.dist-info/top_level.txt
pydea_labjc-0.1.0.dist-info/RECORD
